{
  "pcon24cd": "E14001179",
  "pcon24nm": "Corby and East Northamptonshire",
  "total_votes": null,
  "electorate": null,
  "turnout_pct": null,
  "confirmed": false,
  "votes": [
    {
      "person_id": "113314",
      "person_name": "Lee Barron",
      "image": "https://s3.eu-west-2.amazonaws.com/static-candidates.democracyclub.org.uk/media/images/people/113314/a48014d9-8192-452c-b996-72df2e68134a.png",
      "party_key": "lab",
      "party_name": "Labour Party",
      "votes": null
    },
    {
      "person_id": "113315",
      "person_name": "Eddie McDonald",
      "image": "https://s3.eu-west-2.amazonaws.com/static-candidates.democracyclub.org.uk/media/images/people/115890/05a95532-3300-46bf-b6fb-22854c6d4f16.png",
      "party_key": "ref",
      "party_name": "Reform UK",
      "votes": null
    },
    {
      "person_id": "117834",
      "person_name": "Karen Elizabeth Blott",
      "image": "https://s3.eu-west-2.amazonaws.com/static-candidates.democracyclub.org.uk/media/images/people/117834/35ef6188-174f-49a9-a760-928f846cc449.png",
      "party_key": "other",
      "party_name": "Independent",
      "votes": null
    },
    {
      "person_id": "34121",
      "person_name": "Chris Lofts",
      "image": "https://s3.eu-west-2.amazonaws.com/static-candidates.democracyclub.org.uk/media/images/images/34121.png",
      "party_key": "ld",
      "party_name": "Liberal Democrats",
      "votes": null
    },
    {
      "person_id": "4180",
      "person_name": "Tom Pursglove",
      "image": "https://s3.eu-west-2.amazonaws.com/static-candidates.democracyclub.org.uk/media/images/images/4180-dc3041bb-c18d-4946-abf2-cbaa43d58d2b.png",
      "party_key": "con",
      "party_name": "Conservative and Unionist Party",
      "votes": null
    },
    {
      "person_id": "72693",
      "person_name": "Lee Forster",
      "image": "https://s3.eu-west-2.amazonaws.com/static-candidates.democracyclub.org.uk/media/images/people/72693/530afc15-4a94-4069-a692-9346edf28419.png",
      "party_key": "green",
      "party_name": "Green Party",
      "votes": null
    }
  ]
}