{
  "pcon24cd": "E14001521",
  "pcon24nm": "Stoke-on-Trent North",
  "votes": [
    {
      "person_id": "117631",
      "person_name": "Jag Boyapati",
      "image": "https://s3.eu-west-2.amazonaws.com/static-candidates.democracyclub.org.uk/media/images/people/117631/fe4a7f37-7575-4ad9-92a0-14a72911fe63.png",
      "party_key": "other",
      "party_name": "Independent"
    },
    {
      "person_id": "20069",
      "person_name": "Jonathan Gullis",
      "image": "https://s3.eu-west-2.amazonaws.com/static-candidates.democracyclub.org.uk/media/images/images/20069.png",
      "party_key": "con",
      "party_name": "Conservative and Unionist Party"
    },
    {
      "person_id": "301",
      "person_name": "Lucy Ann Hurds",
      "image": "https://s3.eu-west-2.amazonaws.com/static-candidates.democracyclub.org.uk/media/images/images/301.png",
      "party_key": "ld",
      "party_name": "Liberal Democrats"
    },
    {
      "person_id": "34347",
      "person_name": "David Williams",
      "image": "https://s3.eu-west-2.amazonaws.com/static-candidates.democracyclub.org.uk/media/images/people/95917/07a0e864-91f3-4fb9-9753-7c0cf2555037.png",
      "party_key": "lab",
      "party_name": "Labour Party"
    },
    {
      "person_id": "68519",
      "person_name": "Karl Beresford",
      "image": "https://s3.eu-west-2.amazonaws.com/static-candidates.democracyclub.org.uk/media/images/people/116541/add850ce-7d97-4a15-bc9e-bd7bc689421a.png",
      "party_key": "ref",
      "party_name": "Reform UK"
    },
    {
      "person_id": "96656",
      "person_name": "Josh Harris",
      "image": "https://s3.eu-west-2.amazonaws.com/static-candidates.democracyclub.org.uk/media/images/people/96656/5e0b8fa7-dab6-4e28-90c7-89eabfc4d586.png",
      "party_key": "green",
      "party_name": "Green Party"
    }
  ]
}