{
  "pcon24cd": "E14001284",
  "pcon24nm": "Hertsmere",
  "total_votes": null,
  "electorate": null,
  "turnout_pct": null,
  "confirmed": false,
  "votes": [
    {
      "person_id": "102391",
      "person_name": "Darren Bruce Selkus",
      "image": "https://s3.eu-west-2.amazonaws.com/static-candidates.democracyclub.org.uk/media/images/people/102391/4f5b6ca5-cda2-4739-9a22-105db8db3e92.png",
      "party_key": "ref",
      "party_name": "Reform UK",
      "votes": null
    },
    {
      "person_id": "117196",
      "person_name": "Ray Bolster",
      "image": "/assets/images/missing.svg",
      "party_key": "other",
      "party_name": "Independent",
      "votes": null
    },
    {
      "person_id": "4796",
      "person_name": "Oliver Dowden",
      "image": "https://s3.eu-west-2.amazonaws.com/static-candidates.democracyclub.org.uk/media/images/people/4796/db9f253f-8c86-431e-9cc5-e4f46e1cc5df.png",
      "party_key": "con",
      "party_name": "Conservative and Unionist Party",
      "votes": null
    },
    {
      "person_id": "50322",
      "person_name": "Emma Matanle",
      "image": "https://s3.eu-west-2.amazonaws.com/static-candidates.democracyclub.org.uk/media/images/people/50322/945a9f1e-9777-482d-9277-94e9c5879d15.png",
      "party_key": "ld",
      "party_name": "Liberal Democrats",
      "votes": null
    },
    {
      "person_id": "72000",
      "person_name": "John Humphries",
      "image": "https://s3.eu-west-2.amazonaws.com/static-candidates.democracyclub.org.uk/media/images/images/72000-e019e433-20e3-4c41-9f91-d74db3b7c9d1.png",
      "party_key": "green",
      "party_name": "Green Party",
      "votes": null
    },
    {
      "person_id": "84685",
      "person_name": "Josh Tapper",
      "image": "https://s3.eu-west-2.amazonaws.com/static-candidates.democracyclub.org.uk/media/images/images/84685-a0a426a6-ed0c-49a4-be27-c4b5f48a0bc2.png",
      "party_key": "lab",
      "party_name": "Labour Party",
      "votes": null
    }
  ]
}