{
  "pcon24cd": "E14001310",
  "pcon24nm": "Kensington and Bayswater",
  "votes": [
    {
      "person_id": "113907",
      "person_name": "Joe Powell",
      "image": "https://s3.eu-west-2.amazonaws.com/static-candidates.democracyclub.org.uk/media/images/people/113907/64ef9e17-d81c-4a40-b636-74adcf65a9bf.png",
      "party_key": "lab",
      "party_name": "Labour Party"
    },
    {
      "person_id": "116044",
      "person_name": "Marc Burca",
      "image": "https://s3.eu-west-2.amazonaws.com/static-candidates.democracyclub.org.uk/media/images/people/116044/a5c6e78d-f9f6-47ae-b102-a64e6fabef22.png",
      "party_key": "ref",
      "party_name": "Reform UK"
    },
    {
      "person_id": "117569",
      "person_name": "Una Marie O'Mahony",
      "image": "https://s3.eu-west-2.amazonaws.com/static-candidates.democracyclub.org.uk/media/images/people/117569/34105d62-9eb9-4119-991e-83d8bc07a823.png",
      "party_key": "other",
      "party_name": "Party Of Women"
    },
    {
      "person_id": "3403",
      "person_name": "John Stevens",
      "image": "https://s3.eu-west-2.amazonaws.com/static-candidates.democracyclub.org.uk/media/images/images/3403-3142a79c-79c7-4ee1-a857-01e6601e9531.png",
      "party_key": "other",
      "party_name": "Rejoin EU"
    },
    {
      "person_id": "34309",
      "person_name": "Emma Dent Coad",
      "image": "https://s3.eu-west-2.amazonaws.com/static-candidates.democracyclub.org.uk/media/images/images/34309.png",
      "party_key": "other",
      "party_name": "Independent"
    },
    {
      "person_id": "36132",
      "person_name": "William Houngbo",
      "image": "https://s3.eu-west-2.amazonaws.com/static-candidates.democracyclub.org.uk/media/images/images/36132.png",
      "party_key": "ld",
      "party_name": "Liberal Democrats"
    },
    {
      "person_id": "44168",
      "person_name": "Mona Abdulla Ishag Adam",
      "image": "https://s3.eu-west-2.amazonaws.com/static-candidates.democracyclub.org.uk/media/images/people/44168/6677b090-d777-45b7-8dca-78d5a761a78a.png",
      "party_key": "green",
      "party_name": "Green Party"
    },
    {
      "person_id": "7197",
      "person_name": "Felicity Buchan",
      "image": "https://s3.eu-west-2.amazonaws.com/static-candidates.democracyclub.org.uk/media/images/553bb308a51642637514d640.png",
      "party_key": "con",
      "party_name": "Conservative and Unionist Party"
    },
    {
      "person_id": "72362",
      "person_name": "Roger David Phillips",
      "image": "https://s3.eu-west-2.amazonaws.com/static-candidates.democracyclub.org.uk/media/images/people/72362/ab7216b3-2306-47cd-8e2b-87f5a988eada.png",
      "party_key": "other",
      "party_name": "Christian Peoples Alliance"
    },
    {
      "person_id": "7928",
      "person_name": "Emperor of India Prince Ankit Love",
      "image": "https://s3.eu-west-2.amazonaws.com/static-candidates.democracyclub.org.uk/media/images/people/7928/fc5a0836-720d-4f8a-b448-b307cdee92a9.png",
      "party_key": "other",
      "party_name": "Independent"
    }
  ]
}