{
  "pcon24cd": "E14001071",
  "pcon24nm": "Aylesbury",
  "total_votes": null,
  "electorate": null,
  "turnout_pct": null,
  "confirmed": false,
  "votes": [
    {
      "person_id": "104553",
      "person_name": "Lesley Ann Taylor",
      "image": "https://s3.eu-west-2.amazonaws.com/static-candidates.democracyclub.org.uk/media/images/people/104553/d0648150-93d7-4910-9568-ffd67237e32e.png",
      "party_key": "ref",
      "party_name": "Reform UK",
      "votes": null
    },
    {
      "person_id": "114700",
      "person_name": "Jan Gajdos",
      "image": "https://s3.eu-west-2.amazonaws.com/static-candidates.democracyclub.org.uk/media/images/people/114700/367ba89e-7694-4948-ac60-5f76d4fed482.png",
      "party_key": "other",
      "party_name": "Workers Party of Britain",
      "votes": null
    },
    {
      "person_id": "117174",
      "person_name": "Richard Lewis Wilding",
      "image": "https://s3.eu-west-2.amazonaws.com/static-candidates.democracyclub.org.uk/media/images/people/117174/406a6812-22f6-49da-9d3d-63a03df06fd6.png",
      "party_key": "other",
      "party_name": "Social Democratic Party",
      "votes": null
    },
    {
      "person_id": "35205",
      "person_name": "Julie Elizabeth Atkins",
      "image": "https://s3.eu-west-2.amazonaws.com/static-candidates.democracyclub.org.uk/media/images/people/35205/5a8cfd67-7625-4601-a2de-49cc3c25ad65.png",
      "party_key": "green",
      "party_name": "Green Party",
      "votes": null
    },
    {
      "person_id": "4100",
      "person_name": "Steven Lambert",
      "image": "https://s3.eu-west-2.amazonaws.com/static-candidates.democracyclub.org.uk/media/images/images/4100.png",
      "party_key": "ld",
      "party_name": "Liberal Democrats",
      "votes": null
    },
    {
      "person_id": "72029",
      "person_name": "Rob Butler",
      "image": "https://s3.eu-west-2.amazonaws.com/static-candidates.democracyclub.org.uk/media/images/images/72029-9c934abd-0609-40f8-8b92-0cd461ab0ada.png",
      "party_key": "con",
      "party_name": "Conservative and Unionist Party",
      "votes": null
    },
    {
      "person_id": "78206",
      "person_name": "Laura Elizabeth Kyrke-Smith",
      "image": "https://s3.eu-west-2.amazonaws.com/static-candidates.democracyclub.org.uk/media/images/people/78206/73c952da-8dc0-486b-a960-0f3e28ab2f3c.png",
      "party_key": "lab",
      "party_name": "Labour Party",
      "votes": null
    }
  ]
}