{
  "confirmed": false,
  "declaration_date": null,
  "declaration_time": null,
  "electorate": 71769,
  "last_updated": "2024-07-05T07:30:20.000Z",
  "pcon24cd": "E14001600",
  "pcon24nm": "Wycombe",
  "total_votes": null,
  "turnout_pct": null,
  "votes": [
    {
      "image": "https://s3.eu-west-2.amazonaws.com/static-candidates.democracyclub.org.uk/media/images/people/117796/107c36bb-e21c-4314-be2d-a71b431af1f5.png",
      "party_key": "other",
      "party_name": "Independent",
      "person_id": "117796",
      "person_name": "Mark Smallwood",
      "votes": 214
    },
    {
      "image": "https://s3.eu-west-2.amazonaws.com/static-candidates.democracyclub.org.uk/media/images/images/1481.png",
      "party_key": "con",
      "party_name": "Conservative and Unionist Party",
      "person_id": "1481",
      "person_name": "Steve Baker",
      "votes": 11444
    },
    {
      "image": "https://s3.eu-west-2.amazonaws.com/static-candidates.democracyclub.org.uk/media/images/people/2148/544e92c1-498e-45b9-a0ab-3ff5918b7c60.png",
      "party_key": "lab",
      "party_name": "Labour Party",
      "person_id": "2148",
      "person_name": "Emma Reynolds",
      "votes": 16035
    },
    {
      "image": "https://s3.eu-west-2.amazonaws.com/static-candidates.democracyclub.org.uk/media/images/people/116372/2dc7a083-2d0e-4877-a7ab-ddefe4c5a329.png",
      "party_key": "ref",
      "party_name": "Reform UK",
      "person_id": "27283",
      "person_name": "Richard Phoenix",
      "votes": 4769
    },
    {
      "image": "https://s3.eu-west-2.amazonaws.com/static-candidates.democracyclub.org.uk/media/images/images/71743-4c277c70-a123-4388-a788-07d24a229fce.png",
      "party_key": "other",
      "party_name": "Workers Party of Britain",
      "person_id": "71743",
      "person_name": "Khalil Ahmed",
      "votes": 3344
    },
    {
      "image": "https://s3.eu-west-2.amazonaws.com/static-candidates.democracyclub.org.uk/media/images/images/71744.png",
      "party_key": "ld",
      "party_name": "Liberal Democrats",
      "person_id": "71744",
      "person_name": "Toni Brodelle",
      "votes": 4236
    },
    {
      "image": "https://s3.eu-west-2.amazonaws.com/static-candidates.democracyclub.org.uk/media/images/people/72424/041de716-71f0-4192-950a-06a47d8b3ec3.png",
      "party_key": "other",
      "party_name": "Climate Party",
      "person_id": "72424",
      "person_name": "Ed Gemmell",
      "votes": 489
    },
    {
      "image": "https://s3.eu-west-2.amazonaws.com/static-candidates.democracyclub.org.uk/media/images/people/116829/eec95575-2d77-4a8f-91be-409eeeacfc8a.png",
      "party_key": "other",
      "party_name": "Independent",
      "person_id": "72992",
      "person_name": "Ajaz Rehman",
      "votes": 1913
    },
    {
      "image": "https://s3.eu-west-2.amazonaws.com/static-candidates.democracyclub.org.uk/media/images/images/79799-89205a78-3a86-4cc8-b75b-a676e9acd238.png",
      "party_key": "green",
      "party_name": "Green Party",
      "person_id": "79799",
      "person_name": "Catherine Bunting",
      "votes": 2193
    }
  ]
}
